aws/osml/tile_server_test/__init__.py
aws/osml/tile_server_test/integ_processor.py
aws/osml/tile_server_test/load_processor.py
aws/osml/tile_server_test/processor_base.py
aws/osml/tile_server_test/integ/__init__.py
aws/osml/tile_server_test/integ/test_config.py
aws/osml/tile_server_test/integ/test_tile_server.py
aws/osml/tile_server_test/integ/endpoints/__init__.py
aws/osml/tile_server_test/integ/endpoints/test_create_viewpoint.py
aws/osml/tile_server_test/integ/endpoints/test_delete_viewpoint.py
aws/osml/tile_server_test/integ/endpoints/test_describe_viewpoint.py
aws/osml/tile_server_test/integ/endpoints/test_get_bounds.py
aws/osml/tile_server_test/integ/endpoints/test_get_crop.py
aws/osml/tile_server_test/integ/endpoints/test_get_info.py
aws/osml/tile_server_test/integ/endpoints/test_get_map_tile.py
aws/osml/tile_server_test/integ/endpoints/test_get_metadata.py
aws/osml/tile_server_test/integ/endpoints/test_get_preview.py
aws/osml/tile_server_test/integ/endpoints/test_get_statistics.py
aws/osml/tile_server_test/integ/endpoints/test_get_tile.py
aws/osml/tile_server_test/integ/endpoints/test_list_viewpoints.py
aws/osml/tile_server_test/integ/endpoints/test_update_viewpoint.py
aws/osml/tile_server_test/load/__init__.py
aws/osml/tile_server_test/load/load_test.py
aws/osml/tile_server_test/load/locust_ts_user.py
aws/osml/tile_server_test/utils/__init__.py
aws/osml/tile_server_test/utils/logger.py
aws/osml/tile_server_test/utils/s3_url.py
osml_tile_server_test-0.2.0.dist-info/LICENSE
osml_tile_server_test-0.2.0.dist-info/METADATA
osml_tile_server_test-0.2.0.dist-info/WHEEL
osml_tile_server_test-0.2.0.dist-info/top_level.txt
osml_tile_server_test-0.2.0.dist-info/RECORD
