Metadata-Version: 2.1
Name: osml-tile-server-test
Version: 0.2.0
Summary: Package to run tests against osml-tile-server deployments.
Author: Amazon Web Services
Author-email: aws-osml-admin@amazon.com
License: 
Project-URL: Source, https://github.com/aws-solutions-library-samples/osml-tile-server-test
Project-URL: Tracker, https://github.com/aws-solutions-library-samples/osml-tile-server-test/issues
Classifier: Programming Language :: Python :: 3
Classifier: Operating System :: OS Independent
Requires-Python: >=3.9
License-File: LICENSE
Provides-Extra: test
Requires-Dist: tox ; extra == 'test'
